ecrscan/__init__.py
ecrscan/command.py
ecrscan/utility.py
ECRScan-0.2.2.dist-info/LICENSE
ECRScan-0.2.2.dist-info/METADATA
ECRScan-0.2.2.dist-info/WHEEL
ECRScan-0.2.2.dist-info/entry_points.txt
ECRScan-0.2.2.dist-info/top_level.txt
ECRScan-0.2.2.dist-info/RECORD
