Metadata-Version: 2.1
Name: ECRScan
Version: 0.2.2
Summary: ECR scan utility
Home-page: https://github.com/muckamuck/ecrscan
Author: Chuck Muckamuck
Author-email: Chuck.Muckamuck@gmail.com
License: UNKNOWN
Platform: UNKNOWN
Requires-Dist: boto3 (>=1.10)
Requires-Dist: Click (>=6.7)
Requires-Dist: tabulate (>=0.8)
Requires-Dist: configparser
